setup.py
evnet/__init__.py
evnet/util.py
evnet.egg-info/PKG-INFO
evnet.egg-info/SOURCES.txt
evnet.egg-info/dependency_links.txt
evnet.egg-info/requires.txt
evnet.egg-info/top_level.txt