Metadata-Version: 1.0
Name: evnet
Version: 1.0-2
Summary: evnet is a networking library built on top of pyev (libev)
Home-page: https://github.com/rep/evnet
Author: Mark Schloesser
Author-email: ms@mwcollect.org
License: MIT/BSD/GPL
Keywords: evnet pyev network asynchronous nonblocking event
Platform: UNKNOWN
